idottie/Tools.py
idottie/Translate.py
idottie/__init__.py
idottie/__version__.py
idottie/core.py
idottie-0.0.5.dist-info/LICENSE
idottie-0.0.5.dist-info/METADATA
idottie-0.0.5.dist-info/WHEEL
idottie-0.0.5.dist-info/entry_points.txt
idottie-0.0.5.dist-info/top_level.txt
idottie-0.0.5.dist-info/RECORD
